{
  "id": "bas",
  "type": [
    "wcrp:organisation",
    "wcrp:institution",
    "universal"
  ],
  "validation-key": "BAS",
  "ror": "01rhff309",
  "ui-label": "British Antarctic Survey",
  "url": [
    "https://www.bas.ac.uk/"
  ],
  "established": 1962,
  "kind": "Government",
  "labels": [],
  "aliases": [],
  "acronyms": [
    "BAS"
  ],
  "location": {
    "id": "universal:location/01rhff309",
    "type": "wcrp:location",
    "lat": 52.2,
    "lon": 0.11667,
    "city": "Cambridge",
    "country": [
      "United Kingdom",
      "GB"
    ]
  }
}
