{
    "id": "mri",
    "type": [
        "wcrp:organisation",
        "wcrp:institution",
        "universal"
    ],
    "label": "MRI",
    "ror": "02772kk97",
    "long_label": "Japan Meteorological Agency",
    "url": [
        "http://www.jma.go.jp/jma/indexe.html"
    ],
    "established": 1956,
    "kind": "Other",
    "labels": [],
    "aliases": [
        "Kish\u014d-ch\u014d"
    ],
    "acronyms": [
        "JMA"
    ],
    "location": {
        "id": "universal:location/02772kk97",
        "type": "wcrp:location",
        "lat": 35.6895,
        "lon": 35.6895,
        "city": "Tokyo",
        "country": [
            "Japan",
            "JP"
        ]
    }
}