{
    "@context": "000_context.jsonld",
    "id": "miroc",
    "acronyms": [
        "MIROC"
    ],
    "aliases": [],
    "cmip-acronym": "MIROC",
    "established": null,
    "labels": [],
    "location": {
        "city": "Yokohama, Kanagawa",
        "country": [
            "Japan",
            "JP"
        ],
        "lat": 35.465,
        "lon": 139.620
    },
    "name": "Japan Agency for Marine-Earth Science and Technology, Atmosphere and Ocean Research Institute (The University of Tokyo), and National Institute for Environmental Studies",
    "ror": "059qg2m13",
    "url": [
        "https://www.jamstec.go.jp/e/",
        "https://www.aori.u-tokyo.ac.jp/en/"
    ],
    "type": "institution",
    "drs_name": "MIROC"
}