{
  "@context": "000_context.jsonld",
  "id": "cllcalipso_tavg-840hPa-hxy-air",
  "type": "known_branded_variable",
  "drs_name": "cllcalipso_tavg-840hPa-hxy-air",
  "cf_standard_name": "cloud_area_fraction_in_atmosphere_layer",
  "cf_units": "%",
  "cf_sn_status": "approved",
  "variable_root_name": "cllcalipso",
  "var_def_qualifier": "",
  "branding_suffix_name": "tavg-840hPa-hxy-air",
  "description": "Percentage cloud cover in layer centred on 840hPa\n",
  "dimensions": [
    "longitude",
    "latitude",
    "time",
    "p840"
  ],
  "cell_methods": "area: time: mean where air",
  "cell_measures": "area: areacella",
  "history": ": registered",
  "realm": "",
  "temporal_label": "tavg",
  "vertical_label": "840hPa",
  "horizontal_label": "hxy",
  "area_label": "air",
  "bn_status": "accepted",
  "positive_direction": ""
}