{
  "@context": "000_context.jsonld",
  "id": "fDeforestToAtmos_tavg-u-hxy-lnd",
  "type": "known_branded_variable",
  "drs_name": "fDeforestToAtmos_tavg-u-hxy-lnd",
  "cf_standard_name": "surface_net_upward_mass_flux_of_carbon_dioxide_expressed_as_carbon_due_to_emission_from_anthropogenic_land_use_change",
  "cf_units": "kg m-2 s-1",
  "cf_sn_status": "approved",
  "variable_root_name": "fDeforestToAtmos",
  "var_def_qualifier": "",
  "branding_suffix_name": "tavg-u-hxy-lnd",
  "description": "When land use change results in deforestation of natural vegetation (trees or grasslands) then natural biomass is removed. The treatment of deforested biomass differs significantly across models, but it should be straight-forward to compare deforested biomass across models.\n",
  "dimensions": [
    "longitude",
    "latitude",
    "time"
  ],
  "cell_methods": "area: mean where land time: mean",
  "cell_measures": "area: areacella",
  "history": ": registered",
  "realm": "",
  "temporal_label": "tavg",
  "vertical_label": "u",
  "horizontal_label": "hxy",
  "area_label": "lnd",
  "bn_status": "accepted",
  "positive_direction": ""
}