{
  "@context": "000_context.jsonld",
  "id": "vmo_tavg-l-hxy-sea",
  "type": "known_branded_variable",
  "drs_name": "vmo_tavg-l-hxy-sea",
  "cf_standard_name": "ocean_mass_y_transport",
  "cf_units": "kg s-1",
  "cf_sn_status": "approved",
  "variable_root_name": "vmo",
  "var_def_qualifier": "",
  "branding_suffix_name": "tavg-l-hxy-sea",
  "description": "Y-ward mass transport from residual mean (resolved plus parameterized) advective transport.\n",
  "dimensions": [
    "longitude",
    "latitude",
    "olevel",
    "time"
  ],
  "cell_methods": "area: mean where sea time: mean",
  "cell_measures": "area: areacello volume: volcello",
  "history": ": registered",
  "realm": "",
  "temporal_label": "tavg",
  "vertical_label": "l",
  "horizontal_label": "hxy",
  "area_label": "sea",
  "bn_status": "accepted",
  "positive_direction": ""
}