{
  "@context": "000_context.jsonld",
  "id": "zg500_tpt-500hPa-hxy-air",
  "type": "known_branded_variable",
  "drs_name": "zg500_tpt-500hPa-hxy-air",
  "cf_standard_name": "geopotential_height",
  "cf_units": "m",
  "cf_sn_status": "approved",
  "variable_root_name": "zg500",
  "var_def_qualifier": "",
  "branding_suffix_name": "tpt-500hPa-hxy-air",
  "description": "geopotential height on the 500 hPa surface\n",
  "dimensions": [
    "longitude",
    "latitude",
    "time1",
    "p500"
  ],
  "cell_methods": "area: mean where air time: point",
  "cell_measures": "area: areacella",
  "history": ": registered",
  "realm": "",
  "temporal_label": "tpt",
  "vertical_label": "500hPa",
  "horizontal_label": "hxy",
  "area_label": "air",
  "bn_status": "accepted",
  "positive_direction": ""
}